setup.py
bin/testhello-hello
testhello/__init__.py
testhello/text.py
testhello.egg-info/PKG-INFO
testhello.egg-info/SOURCES.txt
testhello.egg-info/dependency_links.txt
testhello.egg-info/not-zip-safe
testhello.egg-info/top_level.txt