Metadata-Version: 1.0
Name: testhello
Version: 0.3
Summary: Hello test program
Home-page: UNKNOWN
Author: Aqeel
Author-email: testhello@example.com
License: MIT
Platform: UNKNOWN
